rld/__init__.py
rld/app/asset-manifest.json
rld/app/favicon.ico
rld/app/index.html
rld/app/manifest.json
rld/app/precache-manifest.7ac5dab12b8ed23e04f6baec9be89ac8.js
rld/app/robots.txt
rld/app/service-worker.js
rld/app/static/css/2.11829350.chunk.css
rld/app/static/css/2.11829350.chunk.css.map
rld/app/static/css/main.fc910167.chunk.css
rld/app/static/css/main.fc910167.chunk.css.map
rld/app/static/js/2.c53c3bcb.chunk.js
rld/app/static/js/2.c53c3bcb.chunk.js.LICENSE.txt
rld/app/static/js/2.c53c3bcb.chunk.js.map
rld/app/static/js/main.284f6faf.chunk.js
rld/app/static/js/main.284f6faf.chunk.js.map
rld/app/static/js/runtime-main.e6726076.js
rld/app/static/js/runtime-main.e6726076.js.map
rld/app.py
rld/attributation.py
rld/cli.py
rld/config.py
rld/exception.py
rld/model.py
rld/rollout.py
rld/tests/__init__.py
rld/tests/resources/__init__.py
rld/tests/resources/envs.py
rld/tests/resources/models.py
rld/tests/resources/rollouts/__init__.py
rld/tests/resources/rollouts/cartpole.ray_rollout
rld/tests/resources/rollouts/custom_env.ray_rollout
rld/tests/resources/rollouts/pong.ray_rollout
rld/tests/resources/spaces.py
rld/tests/test_app.py
rld/tests/test_attributation.py
rld/tests/test_rollout.py
rld/typing.py
rld-0.1.1.dist-info/entry_points.txt
rld-0.1.1.dist-info/LICENSE
rld-0.1.1.dist-info/WHEEL
rld-0.1.1.dist-info/METADATA
rld-0.1.1.dist-info/RECORD
