Metadata-Version: 2.1
Name: rld
Version: 0.1.1
Summary: A development tool for evaluation and interpretability of reinforcement learning agents.
Home-page: https://github.com/iamhatesz/rld
License: MIT
Keywords: reinforcement learning,development-tools,debugging-tools,interpretability
Author: Tomasz Wrona
Author-email: tomasz@wrona.me
Requires-Python: >=3.7,<4.0
Classifier: Development Status :: 3 - Alpha
Classifier: Framework :: Flask
Classifier: License :: OSI Approved :: MIT License
Classifier: Programming Language :: JavaScript
Classifier: Programming Language :: Python
Classifier: Programming Language :: Python :: 3
Classifier: Programming Language :: Python :: 3.7
Classifier: Programming Language :: Python :: 3.8
Classifier: Topic :: Scientific/Engineering :: Artificial Intelligence
Classifier: Topic :: Software Development :: Debuggers
Classifier: Typing :: Typed
Requires-Dist: captum (>=0.2.0,<0.3.0)
Requires-Dist: click (>=7.1.2,<8.0.0)
Requires-Dist: flask (>=1.1.2,<2.0.0)
Requires-Dist: ray[all] (>=0.8.6,<0.9.0)
Requires-Dist: torch (>=1.6.0,<2.0.0)
Project-URL: Repository, https://github.com/iamhatesz/rld
